<annotation>
	<folder></folder>
	<filename>Copy-of-TUNGRO1_025_jpg.rf.6274af284bd9eb2384344a56204085d8.jpg</filename>
	<path>Copy-of-TUNGRO1_025_jpg.rf.6274af284bd9eb2384344a56204085d8.jpg</path>
	<source>
		<database>roboflow.com</database>
	</source>
	<size>
		<width>416</width>
		<height>416</height>
		<depth>3</depth>
	</size>
	<segmented>0</segmented>
	<object>
		<name>Tungro</name>
		<pose>Unspecified</pose>
		<truncated>0</truncated>
		<difficult>0</difficult>
		<occluded>0</occluded>
		<bndbox>
			<xmin>122</xmin>
			<xmax>331</xmax>
			<ymin>58</ymin>
			<ymax>267</ymax>
		</bndbox>
	</object>
</annotation>
