<annotation>
	<folder></folder>
	<filename>TUNGRO-460-_JPG.rf.3ed9a08d86ca4ad50e47af407cf85390.jpg</filename>
	<path>TUNGRO-460-_JPG.rf.3ed9a08d86ca4ad50e47af407cf85390.jpg</path>
	<source>
		<database>roboflow.com</database>
	</source>
	<size>
		<width>416</width>
		<height>416</height>
		<depth>3</depth>
	</size>
	<segmented>0</segmented>
	<object>
		<name>Tungro</name>
		<pose>Unspecified</pose>
		<truncated>0</truncated>
		<difficult>0</difficult>
		<occluded>0</occluded>
		<bndbox>
			<xmin>127</xmin>
			<xmax>281</xmax>
			<ymin>28</ymin>
			<ymax>417</ymax>
		</bndbox>
		<polygon>
			<x1>280.490368</x1>
			<y1>416</y1>
			<x2>224.938704</x2>
			<y2>301.627297</y2>
			<x3>167.565674</x3>
			<y3>136.48294</y3>
			<x4>125.674256</x4>
			<y4>27.296588</y4>
			<x5>165.744308</x5>
			<y5>169.238845</y5>
			<x6>202.171629</x6>
			<y6>279.790026</y6>
			<x7>255.901926</x7>
			<y7>416</y7>
			<x8>280.490368</x8>
			<y8>416</y8>
		</polygon>
	</object>
</annotation>
